Verify_Signature/Verify_signature.py
Verify_Signature/__init__.py
simple_signature_verify-0.1.0.dist-info/METADATA
simple_signature_verify-0.1.0.dist-info/WHEEL
simple_signature_verify-0.1.0.dist-info/top_level.txt
simple_signature_verify-0.1.0.dist-info/RECORD
