Metadata-Version: 2.1
Name: simple-signature-verify
Version: 0.1.0
Summary: A Python SDK for verifying HMAC signatures
Author: Adithya K
Author-email: adithya.k@setu.co
Classifier: Programming Language :: Python :: 3
Classifier: License :: OSI Approved :: MIT License
Classifier: Operating System :: OS Independent
Requires-Python: >=3.6
